README.rst
setup.py
prps/__init__.py
prps/server_connection.py
prps.egg-info/PKG-INFO
prps.egg-info/SOURCES.txt
prps.egg-info/dependency_links.txt
prps.egg-info/not-zip-safe
prps.egg-info/requires.txt
prps.egg-info/top_level.txt