Metadata-Version: 1.0
Name: prps
Version: 0.0.5
Summary: Connect to Pepper via ssh and run the rock paper scissors game.
Home-page: https://github.com/D7017E/Rock-Paper-Scissors
Author: D7017E
Author-email: bersim-8@student.ltu.se
License: UNKNOWN
Platform: UNKNOWN
